cul_spectrum/__init__.py
cul_spectrum/cli.py
cul_spectrum/client.py
cul_spectrum-1.0.2.dist-info/LICENSE
cul_spectrum-1.0.2.dist-info/METADATA
cul_spectrum-1.0.2.dist-info/WHEEL
cul_spectrum-1.0.2.dist-info/entry_points.txt
cul_spectrum-1.0.2.dist-info/top_level.txt
cul_spectrum-1.0.2.dist-info/RECORD
