Metadata-Version: 2.1
Name: cul-spectrum
Version: 1.0.2
Summary: Concordia University Library Spectrum Client
Home-page: https://github.com/artefactual-labs/cul-spectrum
Author: Artefactual Systems, Inc.
Author-email: info@artefactual.com
Project-URL: Bug Tracker, https://github.com/artefactual-labs/cul-spectrum/issues
Classifier: Programming Language :: Python :: 3
Classifier: License :: OSI Approved :: GNU General Public License v3 or later (GPLv3+)
Classifier: Operating System :: OS Independent
Requires-Python: >=3.8
License-File: LICENSE
Requires-Dist: Click >=8.0.4
